bilby_rust-0.1.1.dist-info/METADATA
bilby_rust-0.1.1.dist-info/WHEEL
bilby_rust/__init__.py
bilby_rust/bilby_rust.cpython-39-darwin.so
bilby_rust-0.1.1.dist-info/RECORD
