Metadata-Version: 2.4
Name: bilby_rust
Version: 0.1.1
Requires-Dist: numpy
Requires-Dist: pytest ; extra == 'test'
Requires-Dist: pytest-cov ; extra == 'test'
Requires-Dist: bilby-cython ; extra == 'test'
Requires-Dist: bilby ; extra == 'test'
Requires-Dist: scipy<1.15 ; extra == 'test'
Provides-Extra: test
Summary: Rust implementation of domain-specific geometrical operations for Bilby to mirror the functionality in bilby-cython using PyO3.
Author: Colm Talbot <talbotcolm@gmail.com>
Author-email: Colm Talbot <talbotcolm@gmail.com>
License: MIT
Requires-Python: >=3.7
Project-URL: Source Code, https://github.com/ColmTalbot/bilby_rust
